epochmonitor/__init__.py
epochmonitor/monitor.py
epochmonitor-1.0.0.dist-info/licenses/LICENSE
epochmonitor-1.0.0.dist-info/METADATA
epochmonitor-1.0.0.dist-info/WHEEL
epochmonitor-1.0.0.dist-info/top_level.txt
epochmonitor-1.0.0.dist-info/RECORD
