Metadata-Version: 2.4
Name: epochmonitor
Version: 1.0.0
Summary: A simple and versatile monitor/profiler for model training loops.
Author-email: Varun Patani <varunpatani2004356@gmail.com>
Project-URL: Homepage, https://github.com/your_username/epochmonitor
Project-URL: Bug Tracker, https://github.com/your_username/epochmonitor/issues
Classifier: Programming Language :: Python :: 3
Classifier: License :: OSI Approved :: MIT License
Classifier: Operating System :: OS Independent
Classifier: Intended Audience :: Developers
Classifier: Topic :: System :: Monitoring
Requires-Python: >=3.7
License-File: LICENSE
Requires-Dist: psutil>=5.9.0
Requires-Dist: nvidia-ml-py>=11.450.51
Dynamic: license-file
